mollu/__init__.py
projectmx-0.0.2.dist-info/LICENSE
projectmx-0.0.2.dist-info/METADATA
projectmx-0.0.2.dist-info/WHEEL
projectmx-0.0.2.dist-info/top_level.txt
projectmx-0.0.2.dist-info/RECORD
